chainmeta/__init__.py
chainmeta/artifact.py
chainmeta/constants.py
chainmeta/db.py
chainmeta/logger.py
chainmeta/metadata.py
chainmeta/validator.py
chainmeta/config/__init__.py
chainmeta/config/categories.json
chainmeta/config/chains.json
chainmeta/config/entities.json
chainmeta/config/sources.json
chainmeta/contrib/chaintool.py
chainmeta/contrib/chaintool_schema.json
chainmeta/contrib/messari.py
chainmeta/contrib/messari_schema.json
chainmeta/schema/__init__.py
chainmeta/schema/artifact_schema.json
chainmeta/schema/meta_schema.json
chainmeta-0.0.5.post1.dist-info/LICENSE
chainmeta-0.0.5.post1.dist-info/METADATA
chainmeta-0.0.5.post1.dist-info/WHEEL
chainmeta-0.0.5.post1.dist-info/top_level.txt
chainmeta-0.0.5.post1.dist-info/RECORD
