Metadata-Version: 2.1
Name: chainmeta
Version: 0.0.5.post1
Summary: Onchain metadata exchange protocol
Project-URL: Homepage, https://github.com/microscopexyz/chainmeta-core
Project-URL: Issues, https://github.com/microscopexyz/chainmeta-core/issues
Classifier: Programming Language :: Python :: 3
Classifier: License :: OSI Approved :: Apache Software License
Classifier: Operating System :: OS Independent
Requires-Python: >=3.9
License-File: LICENSE
Requires-Dist: jsonschema
Requires-Dist: python-dateutil
Requires-Dist: sqlalchemy
Requires-Dist: unsync
